cruds/__init__.py
cruds/models.py
cruds/urls.py
cruds/utils.py
cruds/views.py
cruds/static/css/cruds.css
cruds/static/js/cruds.js
cruds/templates/cruds/_form.html
cruds/templates/cruds/base.html
cruds/templates/cruds/create.html
cruds/templates/cruds/delete.html
cruds/templates/cruds/detail.html
cruds/templates/cruds/list.html
cruds/templates/cruds/update.html
cruds/templates/cruds/templatetags/crud_fields.html
cruds/templatetags/__init__.py
cruds/templatetags/crud_tags.py
django_cruds-3.0.0.dist-info/AUTHORS.rst
django_cruds-3.0.0.dist-info/LICENSE
django_cruds-3.0.0.dist-info/METADATA
django_cruds-3.0.0.dist-info/WHEEL
django_cruds-3.0.0.dist-info/top_level.txt
django_cruds-3.0.0.dist-info/RECORD
