Metadata-Version: 2.1
Name: django-cruds
Version: 3.0.0
Summary: django-cruds is simple drop-in django app that creates CRUD for faster prototyping.
Home-page: https://github.com/bmihelac/django-cruds
Author: Bojan Mihelac
Author-email: bmihelac@mihelac.org
License: BSD
Keywords: django-cruds
Classifier: Development Status :: 2 - Pre-Alpha
Classifier: Framework :: Django
Classifier: Intended Audience :: Developers
Classifier: License :: OSI Approved :: BSD License
Classifier: Natural Language :: English
Classifier: Programming Language :: Python :: 3
Classifier: Programming Language :: Python :: 3.8
Classifier: Programming Language :: Python :: 3.9
Classifier: Programming Language :: Python :: 3.10
Classifier: Programming Language :: Python :: 3.11
Classifier: Programming Language :: Python :: 3.12
License-File: LICENSE
License-File: AUTHORS.rst
Requires-Dist: Django<5,>=4.2
